linuxforhealth/csvtofhir/__init__.py
linuxforhealth/csvtofhir/config.py
linuxforhealth/csvtofhir/converter.py
linuxforhealth/csvtofhir/support.py
linuxforhealth/csvtofhir/cli/__init__.py
linuxforhealth/csvtofhir/cli/convert.py
linuxforhealth/csvtofhir/cli/main.py
linuxforhealth/csvtofhir/cli/validate.py
linuxforhealth/csvtofhir/fhirrs/__init__.py
linuxforhealth/csvtofhir/fhirrs/allergy_intolerance.py
linuxforhealth/csvtofhir/fhirrs/basic.py
linuxforhealth/csvtofhir/fhirrs/condition.py
linuxforhealth/csvtofhir/fhirrs/converter.py
linuxforhealth/csvtofhir/fhirrs/diagnostic_report.py
linuxforhealth/csvtofhir/fhirrs/document_reference.py
linuxforhealth/csvtofhir/fhirrs/encounter.py
linuxforhealth/csvtofhir/fhirrs/immunization.py
linuxforhealth/csvtofhir/fhirrs/location.py
linuxforhealth/csvtofhir/fhirrs/medication_administration.py
linuxforhealth/csvtofhir/fhirrs/medication_request.py
linuxforhealth/csvtofhir/fhirrs/medication_statement.py
linuxforhealth/csvtofhir/fhirrs/medication_use.py
linuxforhealth/csvtofhir/fhirrs/meta.py
linuxforhealth/csvtofhir/fhirrs/observation.py
linuxforhealth/csvtofhir/fhirrs/organization.py
linuxforhealth/csvtofhir/fhirrs/patient.py
linuxforhealth/csvtofhir/fhirrs/practitioner.py
linuxforhealth/csvtofhir/fhirrs/procedure.py
linuxforhealth/csvtofhir/fhirrs/unstructured.py
linuxforhealth/csvtofhir/fhirutils/__init__.py
linuxforhealth/csvtofhir/fhirutils/csv_record_validator.py
linuxforhealth/csvtofhir/fhirutils/csv_utils.py
linuxforhealth/csvtofhir/fhirutils/fhir_constants.py
linuxforhealth/csvtofhir/fhirutils/fhir_identifier_utils.py
linuxforhealth/csvtofhir/fhirutils/fhir_utils.py
linuxforhealth/csvtofhir/model/__init__.py
linuxforhealth/csvtofhir/model/base.py
linuxforhealth/csvtofhir/model/contract.py
linuxforhealth/csvtofhir/model/csv/__init__.py
linuxforhealth/csvtofhir/model/csv/allergy_intolerance.py
linuxforhealth/csvtofhir/model/csv/base.py
linuxforhealth/csvtofhir/model/csv/basic.py
linuxforhealth/csvtofhir/model/csv/condition.py
linuxforhealth_csvtofhir-1.2.0.dist-info/LICENSE
linuxforhealth_csvtofhir-1.2.0.dist-info/METADATA
linuxforhealth_csvtofhir-1.2.0.dist-info/WHEEL
linuxforhealth_csvtofhir-1.2.0.dist-info/entry_points.txt
linuxforhealth_csvtofhir-1.2.0.dist-info/top_level.txt
linuxforhealth_csvtofhir-1.2.0.dist-info/RECORD
