Metadata-Version: 2.1
Name: linuxforhealth-csvtofhir
Version: 1.2.0
Summary: Maps and converts delimited data to FHIR resources.
Home-page: https://github.com/LinuxForHealth/CsvToFHIR
License: Apache 2.0 License
Keywords: linuxforhealth,fhir,csv,healthit,edi,hl7
Platform: any
Classifier: Development Status :: 5 - Production/Stable
Classifier: License :: OSI Approved :: Apache Software License
Classifier: Operating System :: OS Independent
Classifier: Programming Language :: Python :: 3.9
Classifier: Programming Language :: Python :: 3.10
Classifier: Intended Audience :: Healthcare Industry
Classifier: Intended Audience :: Developers
Classifier: Intended Audience :: Information Technology
Requires-Python: >=3.9
License-File: LICENSE
Requires-Dist: deepdiff (<6.0,>=5.8)
Requires-Dist: fhir.resources (<7.0,>=6.4)
Requires-Dist: pandas (<1.5,>=1.4)
Requires-Dist: pydantic (<2.0,>=1.9)
Requires-Dist: python-dotenv (<1.0,>=0.20)
Requires-Dist: python-dateutil (<3.0,>=2.8)
Requires-Dist: pytz (==2022.1)
Provides-Extra: dev
Requires-Dist: pytest (<8.0,>=7.1) ; extra == 'dev'
Requires-Dist: flake8 (<5.0,>=4.0) ; extra == 'dev'
Requires-Dist: autopep8 (<2.0,>=1.6) ; extra == 'dev'
Requires-Dist: isort (<6.0,>=5.10) ; extra == 'dev'
Provides-Extra: notebook
Requires-Dist: jupyterlab ; extra == 'notebook'
Provides-Extra: optimized-streaming
Requires-Dist: smart-open (>=6.2.0) ; extra == 'optimized-streaming'
